dhali/__init__.py
dhali/create_signed_claim.py
dhali/dhali_channel_manager.py
dhali_py-1.0.3.dist-info/LICENSE
dhali_py-1.0.3.dist-info/METADATA
dhali_py-1.0.3.dist-info/WHEEL
dhali_py-1.0.3.dist-info/entry_points.txt
dhali_py-1.0.3.dist-info/top_level.txt
dhali_py-1.0.3.dist-info/RECORD
