Metadata-Version: 2.1
Name: dhali-py
Version: 1.0.3
Summary: A Python package for interfacing with Dhali
Home-page: https://github.com/Dhali-org/Dhali-py
Author: Dhali Holdings Ltd
Author-email: engagement@dhali.io
License: BSD 3-Clause License
Project-URL: Documentation, https://pyscaffold.org/
Platform: any
Classifier: Development Status :: 4 - Beta
Classifier: Programming Language :: Python
License-File: LICENSE
Requires-Dist: xrpl-py ==2.5.0
Requires-Dist: importlib-metadata ; python_version < "3.8"
Provides-Extra: testing
Requires-Dist: setuptools ; extra == 'testing'
Requires-Dist: pytest ; extra == 'testing'
Requires-Dist: pytest-cov ; extra == 'testing'
